{"fake_tenerife": {"count": 3, "embeddings": [{"0": 0}, {"0": 1}, {"0": 3}]}, "fake_athens": {"count": 3, "embeddings": [{"0": 0}, {"0": 2}, {"0": 3}]}, "fake_belem": {"count": 2, "embeddings": [{"0": 0}, {"0": 3}]}, "fake_bogota": {"count": 2, "embeddings": [{"0": 0}, {"0": 3}]}, "fake_burlington": {"count": 3, "embeddings": [{"0": 0}, {"0": 1}, {"0": 2}]}, "fake_essex": {"count": 2, "embeddings": [{"0": 0}, {"0": 2}]}, "fake_lima": {"count": 2, "embeddings": [{"0": 0}, {"0": 4}]}, "fake_london": {"count": 3, "embeddings": [{"0": 0}, {"0": 1}, {"0": 2}]}, "fake_manila": {"count": 1, "embeddings": [{"0": 0}]}, "fake_ourense": {"count": 2, "embeddings": [{"0": 0}, {"0": 4}]}, "fake_quito": {"count": 3, "embeddings": [{"0": 0}, {"0": 2}, {"0": 3}]}, "fake_rome": {"count": 2, "embeddings": [{"0": 0}, {"0": 3}]}, "fake_santiago": {"count": 2, "embeddings": [{"0": 0}, {"0": 2}]}, "fake_vigo": {"count": 2, "embeddings": [{"0": 0}, {"0": 4}]}, "fake_yorktown": {"count": 2, "embeddings": [{"0": 0}, {"0": 4}]}, "count": 34}